pybrboleto/__init__.py
pybrboleto/data.py
pybrboleto/html.py
pybrboleto/pdf.py
pybrboleto/bank/__init__.py
pybrboleto/bank/bancodobrasil.py
pybrboleto/bank/banrisul.py
pybrboleto/bank/bradesco.py
pybrboleto/bank/caixa.py
pybrboleto/bank/caixa_sigcb.py
pybrboleto/bank/cecred.py
pybrboleto/bank/hsbc.py
pybrboleto/bank/itau.py
pybrboleto/bank/real.py
pybrboleto/bank/santander.py
pybrboleto/bank/sicoob.py
pybrboleto/bank/sicredi.py
pybrboleto/django/__init__.py
pybrboleto/django/admin.py
pybrboleto/django/models.py
pybrboleto/django/views.py
pybrboleto/media/logo_bancobradesco.jpg
pybrboleto/media/logo_bancocaixa.jpg
pybrboleto/media/logo_bancohsbc.jpg
pybrboleto/media/logo_bancoreal.jpg
pybrboleto/media/logo_banrisul.jpg
pybrboleto/media/logo_bb.jpg
pybrboleto/media/logo_cecred.jpg
pybrboleto/media/logo_itau.jpg
pybrboleto/media/logo_santander.jpg
pybrboleto/media/logo_sicoob.jpg
pybrboleto/media/logo_sicredi.jpg
pybrboleto/templates/head.html
pybrboleto/templates/recibo_caixa.html
pybrboleto/templates/recibo_sacado.html
pybrboleto-1.0.7.data/scripts/html_pybrboleto_sample.py
pybrboleto-1.0.7.data/scripts/pdf_pybrboleto_sample.py
tests/__init__.py
tests/alltests.py
tests/test_banco_banrisul.py
tests/test_banco_bradesco.py
tests/test_banco_caixa.py
tests/test_banco_do_brasil.py
tests/test_banco_hsbc.py
tests/test_banco_hsbc_com_registro.py
tests/test_banco_itau.py
tests/test_banco_real.py
tests/test_banco_santander.py
tests/test_banco_sicoob.py
tests/test_banco_sicredi.py
tests/testutils.py
tests/xml/BoletoBB-expected.xml
tests/xml/BoletoBanrisul-expected.xml
tests/xml/BoletoBradesco-expected.xml
tests/xml/BoletoCaixa-expected.xml
tests/xml/BoletoHsbc-expected.xml
tests/xml/BoletoHsbcComRegistro-expected.xml
tests/xml/BoletoItau-expected.xml
tests/xml/BoletoReal-expected.xml
tests/xml/BoletoSantander-expected.xml
tests/xml/BoletoSicoob-expected.xml
tests/xml/BoletoSicredi-expected.xml
tests/xml/Triplo-BoletoBB-expected.xml
tests/xml/Triplo-BoletoBanrisul-expected.xml
pybrboleto-1.0.7.dist-info/LICENSE
pybrboleto-1.0.7.dist-info/METADATA
pybrboleto-1.0.7.dist-info/WHEEL
pybrboleto-1.0.7.dist-info/top_level.txt
pybrboleto-1.0.7.dist-info/RECORD
