Metadata-Version: 2.1
Name: pybrboleto
Version: 1.0.7
Summary: Pacote para gerar Boletos.
Home-page: https://github.com/kanekoinformatica/pybrboleto
Author: Kaneko Informatica
Author-email: kaneko@kaneko.com.br
License: BSD
Download-URL: http://pypi.python.org/pypi/pybrboleto
Platform: any
Classifier: Development Status :: 4 - Beta
Classifier: Operating System :: OS Independent
Classifier: Intended Audience :: Developers
Classifier: Intended Audience :: Financial and Insurance Industry
Classifier: Operating System :: OS Independent
Classifier: License :: OSI Approved :: BSD License
Classifier: Natural Language :: Portuguese (Brazilian)
Classifier: Programming Language :: Python
Classifier: Programming Language :: Python :: 3
Classifier: Topic :: Office/Business :: Financial
Classifier: Topic :: Software Development :: Libraries :: Python Modules
Classifier: Framework :: Django
Provides: pybrboleto
Requires-Dist: reportlab
